morb/__init__.py
morb/applications/__init__.py
morb/applications/lidar_post_detect/__init__.py
morb/applications/lidar_post_detect/convert2tflite.py
morb/applications/lidar_post_detect/main.py
morb/applications/lidar_post_detect/params.py
morb/applications/lidar_post_detect/test.py
morb/applications/lidar_segmentation/__init__.py
morb/applications/lidar_segmentation/main.py
morb/applications/lidar_segmentation/viz_pred.py
morb/applications/mono_depth/__init__.py
morb/applications/mono_depth/main.py
morb/applications/person_segmentation/__init__.py
morb/applications/person_segmentation/main.py
morb/applications/pointcloud_classification/__init__.py
morb/applications/pointcloud_classification/main.py
morb/applications/scene_segmentation/__init__.py
morb/applications/scene_segmentation/main.py
morb/custom_losses/__init__.py
morb/custom_losses/pytorch/__init__.py
morb/custom_losses/pytorch/depth.py
morb/custom_losses/pytorch/pointnetloss.py
morb/custom_losses/pytorch/segment.py
morb/custom_losses/tensorflow/__init__.py
morb/custom_losses/tensorflow/feature_detect.py
morb/datacreators/__init__.py
morb/datacreators/ai2thor/__init__.py
morb/datacreators/ai2thor/create_dataset.py
morb/datacreators/ai2thor/register_pcds.py
morb/datacreators/lidar_contours/__init__.py
morb/datacreators/lidar_contours/human_contours.py
morb/datacreators/utils/__init__.py
morb/datacreators/utils/cv_annotator.py
morb/dataloaders/__init__.py
morb/dataloaders/ade20k.py
morb/dataloaders/cihp.py
morb/dataloaders/coco.py
morb/dataloaders/diode.py
morb/dataloaders/imgcsvloader.py
morb/dataloaders/modelnet.py
morb/dataloaders/nyuv2.py
morb/dataloaders/shapenet.py
morb/dataloaders/lidar_datasets/__init__.py
morb/dataloaders/lidar_datasets/loader.py
morb/dataloaders/lidar_datasets/nuscenes.py
morb/dataloaders/utils/__init__.py
morb/dataloaders/utils/augmentations.py
morb/dataloaders/utils/pointcloud_voxelize.py
morb/dataloaders/utils/read_supervisely.py
morb/misctools/__init__.py
morb-0.0.2.dist-info/METADATA
morb-0.0.2.dist-info/WHEEL
morb-0.0.2.dist-info/top_level.txt
morb-0.0.2.dist-info/RECORD
