Metadata-Version: 2.1
Name: morb
Version: 0.0.2
Summary: MOdules for Robot Brain (MORB)- A modular perception library for machine learning in robotics use cases
Home-page: https://github.com/Homagn/morb
Author: Homagni Saha
Author-email: Homagni Saha <homagnisaha@gmail.com>
Project-URL: Homepage, https://github.com/Homagn/morb
Classifier: Programming Language :: Python :: 3
Classifier: License :: OSI Approved :: MIT License
Classifier: Operating System :: OS Independent
Requires-Python: >=3.7
